tests/__init__.py
tests/test_zoompy.py
zoompy/__init__.py
zoompy/zoompy.py
zoompy-1.0.dist-info/LICENSE
zoompy-1.0.dist-info/METADATA
zoompy-1.0.dist-info/WHEEL
zoompy-1.0.dist-info/top_level.txt
zoompy-1.0.dist-info/RECORD
