Metadata-Version: 2.1
Name: zoompy
Version: 1.0
Summary: Get data from Ergast
Home-page: https://github.com/Mnayu/zoompy
Author: Abhimanyu Bhadauria
Author-email: abhimanyu2911@gmail.com
License: UNKNOWN
Platform: UNKNOWN
Classifier: Programming Language :: Python :: 3
Classifier: License :: OSI Approved :: MIT License
Classifier: Operating System :: OS Independent
License-File: LICENSE
